{
	"agcgw_all":{
		"CN":"connect-drcn.dbankcloud.cn",
		"CN_back":"connect-drcn.hispace.hicloud.com",
		"DE":"connect-dre.dbankcloud.cn",
		"DE_back":"connect-dre.hispace.hicloud.com",
		"RU":"connect-drru.dbankcloud.cn",
		"RU_back":"connect-drru.hispace.hicloud.com",
		"SG":"connect-dra.dbankcloud.cn",
		"SG_back":"connect-dra.hispace.hicloud.com"
	},
	"client":{
		"cp_id":"2640084000021046714",
		"product_id":"737518067793771546",
		"client_id":"769472215518300608",
		"client_secret":"6F10FBDECFD7EE3FDCEED3C0660AA8F1B98790CF13F970F92A4B4E1711F57ACE",
		"project_id":"737518067793771546",
		"app_id":"105026881",
		"api_key":"CwEAAAAAmAO8vVfrFAufAoSORBi6Nsee3ZkXGW80mC/bVVzMyMe6igxWja3X4f4VlrDyZoVde97oie2tJkH/76EE9X9WpAoEMZk=",
		"package_name":"com.ql.appquanlycuahang"
	},
	"oauth_client":{
		"client_id":"105026881",
		"client_type":1
	},
	"app_info":{
		"app_id":"105026881",
		"package_name":"com.ql.appquanlycuahang"
	},
	"configuration_version":"3.0",
	"appInfos":[
		{
			"package_name":"com.ql.appquanlycuahang",
			"client":{
				"app_id":"105026881"
			},
			"app_info":{
				"package_name":"com.ql.appquanlycuahang",
				"app_id":"105026881"
			},
			"oauth_client":{
				"client_type":1,
				"client_id":"105026881"
			}
		}
	]
}